privex/__init__.py
privex/db/__init__.py
privex/db/base.py
privex/db/postgres.py
privex/db/settings.py
privex/db/sqlite.py
privex/db/types.py
privex/db/query/__init__.py
privex/db/query/base.py
privex/db/query/postgres.py
privex/db/query/sqlite.py
privex/db/query/asyncx/__init__.py
privex/db/query/asyncx/base.py
privex/db/query/asyncx/sqlite.py
privex_db-0.9.2.dist-info/LICENSE
privex_db-0.9.2.dist-info/METADATA
privex_db-0.9.2.dist-info/WHEEL
privex_db-0.9.2.dist-info/top_level.txt
privex_db-0.9.2.dist-info/RECORD
