Metadata-Version: 2.1
Name: privex-db
Version: 0.9.2
Summary: Privex's Python Database helpers and wrappers (mini ORM)
Home-page: https://github.com/Privex/python-db
Author: Chris (Someguy123) @ Privex
Author-email: chris@privex.io
License: MIT
Platform: UNKNOWN
Classifier: Programming Language :: Python :: 3
Classifier: Programming Language :: Python :: 3.6
Classifier: Programming Language :: Python :: 3.7
Classifier: Programming Language :: Python :: 3.8
Classifier: License :: OSI Approved :: MIT License
Classifier: Operating System :: OS Independent
Requires-Dist: privex-helpers (>=2.6.0)
Requires-Dist: aiosqlite
Requires-Dist: async-property
Requires-Dist: python-dateutil
Requires-Dist: pytz
Requires-Dist: typing-extensions
Provides-Extra: async
Requires-Dist: nest-asyncio ; extra == 'async'
Provides-Extra: nest
Requires-Dist: nest-asyncio ; extra == 'nest'
Provides-Extra: postgres
Requires-Dist: psycopg2 ; extra == 'postgres'
